Sudoku_Solver/__init__.py
Sudoku_Solver/main_sudoku.py
prvi_pokusaj1-0.0.1.dist-info/METADATA
prvi_pokusaj1-0.0.1.dist-info/WHEEL
prvi_pokusaj1-0.0.1.dist-info/top_level.txt
prvi_pokusaj1-0.0.1.dist-info/RECORD
