Metadata-Version: 2.1
Name: prvi-pokusaj1
Version: 0.0.1
Summary: Sudoku solver with number detection and recognision.
Home-page: UNKNOWN
Author: Nikola Ignjatovic
Author-email: <nikola444555@gmail.com>
License: UNKNOWN
Keywords: python,video,stream,video stream,camera stream,sockets
Platform: UNKNOWN
Classifier: Development Status :: 1 - Planning
Classifier: Intended Audience :: Developers
Classifier: Programming Language :: Python :: 3
Classifier: Operating System :: Unix
Classifier: Operating System :: MacOS :: MacOS X
Classifier: Operating System :: Microsoft :: Windows
Requires-Dist: opencv-python
Requires-Dist: keras
Requires-Dist: imutils
